{"city":"Scottsdale","mascot":"Glass Lionfish","players":[{"number":89,"first_name":"Dax","middle_name":"Ismael","nick_name":"","last_name":"Richardson","position":"first base","is_pitcher":false},{"number":18,"first_name":"Marcel","middle_name":"Edwin","nick_name":"","last_name":"Gutierrez","position":"second base","is_pitcher":false},{"number":15,"first_name":"Andrew","middle_name":"Maxwell","nick_name":"","last_name":"Perez","position":"third base","is_pitcher":false},{"number":45,"first_name":"Erick","middle_name":"Knox","nick_name":"","last_name":"Hall","position":"short stop","is_pitcher":false},{"number":29,"first_name":"Maximo","middle_name":"Diego","nick_name":"","last_name":"Miller","position":"catcher","is_pitcher":false},{"number":54,"first_name":"Fabian","middle_name":"Erick","nick_name":"","last_name":"Jackson","position":"left field","is_pitcher":false},{"number":89,"first_name":"Kaden","middle_name":"Fernando","nick_name":"","last_name":"Evans","position":"center field","is_pitcher":false},{"number":18,"first_name":"Kingston","middle_name":"Jeremy","nick_name":"","last_name":"Kim","position":"right field","is_pitcher":false},{"number":21,"first_name":"William","middle_name":"Bodhi","nick_name":"","last_name":"Thompson","position":"pitcher 1","is_pitcher":true},{"number":66,"first_name":"King","middle_name":"Oscar","nick_name":"","last_name":"Nelson","position":"pitcher 2","is_pitcher":true},{"number":29,"first_name":"Preston","middle_name":"Oscar","nick_name":"","last_name":"Green","position":"pitcher 3","is_pitcher":true},{"number":68,"first_name":"Quentin","middle_name":"Lucas","nick_name":"","last_name":"Cook","position":"pitcher 4","is_pitcher":true},{"number":66,"first_name":"Declan","middle_name":"Remington","nick_name":"","last_name":"Davis","position":"pitcher 5","is_pitcher":true},{"number":25,"first_name":"Ronin","middle_name":"Paul","nick_name":"","last_name":"Sanchez","position":"pitcher 6","is_pitcher":true},{"number":49,"first_name":"Ezequiel","middle_name":"Declan","nick_name":"","last_name":"Cox","position":"pitcher 7","is_pitcher":true},{"number":8,"first_name":"Eliam","middle_name":"Walker","nick_name":"Spring","last_name":"Flores","position":"pitcher 8","is_pitcher":true}]}